poutyne/__init__.py
poutyne/plotting.py
poutyne/utils.py
poutyne/version.py
poutyne/warning_manager.py
poutyne/framework/__init__.py
poutyne/framework/experiment.py
poutyne/framework/iterators.py
poutyne/framework/model.py
poutyne/framework/model_bundle.py
poutyne/framework/optimizers.py
poutyne/framework/callbacks/__init__.py
poutyne/framework/callbacks/_utils.py
poutyne/framework/callbacks/best_model_restore.py
poutyne/framework/callbacks/callbacks.py
poutyne/framework/callbacks/checkpoint.py
poutyne/framework/callbacks/clip_grad.py
poutyne/framework/callbacks/color_formatting.py
poutyne/framework/callbacks/delay.py
poutyne/framework/callbacks/earlystopping.py
poutyne/framework/callbacks/gradient_logger.py
poutyne/framework/callbacks/gradient_tracker.py
poutyne/framework/callbacks/lambda_.py
poutyne/framework/callbacks/logger.py
poutyne/framework/callbacks/lr_scheduler.py
poutyne/framework/callbacks/mlflow_logger.py
poutyne/framework/callbacks/notification.py
poutyne/framework/callbacks/periodic.py
poutyne/framework/callbacks/policies.py
poutyne/framework/callbacks/progress.py
poutyne/framework/callbacks/progress_bar.py
poutyne/framework/callbacks/terminate_on_nan.py
poutyne/framework/callbacks/wandb_logger.py
poutyne/framework/metrics/__init__.py
poutyne/framework/metrics/base.py
poutyne/framework/metrics/decomposable.py
poutyne/framework/metrics/metric_argument_indexing.py
poutyne/framework/metrics/metrics_registering.py
poutyne/framework/metrics/pytorch_loss_functions_registering.py
poutyne/framework/metrics/utils.py
poutyne/framework/metrics/predefined/__init__.py
poutyne/framework/metrics/predefined/accuracy.py
poutyne/framework/metrics/predefined/bincount.py
poutyne/framework/metrics/predefined/fscores.py
poutyne/framework/metrics/predefined/sklearn_metrics.py
poutyne/layers/__init__.py
poutyne/layers/utils.py
poutyne-1.17.4.dist-info/licenses/LICENSE
tests/__init__.py
tests/context.py
tests/test_plotting.py
tests/test_utils.py
tests/utils.py
tests/framework/__init__.py
tests/framework/base.py
poutyne-1.17.4.dist-info/METADATA
poutyne-1.17.4.dist-info/WHEEL
poutyne-1.17.4.dist-info/top_level.txt
poutyne-1.17.4.dist-info/RECORD
