Metadata-Version: 2.4
Name: Poutyne
Version: 1.17.4
Summary: A simplified framework and utilities for PyTorch.
Home-page: https://poutyne.org
Download-URL: https://github.com/GRAAL-Research/poutyne/archive/v1.17.4.zip
Author: Frédérik Paradis
Author-email: fredy_14@live.fr
License: LGPLv3
Classifier: Development Status :: 5 - Production/Stable
Classifier: Intended Audience :: Developers
Classifier: Intended Audience :: Education
Classifier: Intended Audience :: Science/Research
Classifier: License :: OSI Approved :: GNU Lesser General Public License v3 (LGPLv3)
Classifier: Programming Language :: Python :: 3
Classifier: Programming Language :: Python :: 3.8
Classifier: Programming Language :: Python :: 3.9
Classifier: Programming Language :: Python :: 3.10
Classifier: Programming Language :: Python :: 3.11
Classifier: Programming Language :: Python :: 3.12
Classifier: Topic :: Software Development :: Libraries
Classifier: Topic :: Software Development :: Libraries :: Python Modules
Classifier: Topic :: Scientific/Engineering
Classifier: Topic :: Scientific/Engineering :: Artificial Intelligence
Requires-Python: >=3.8
License-File: LICENSE
Requires-Dist: numpy
Requires-Dist: torch
Requires-Dist: torchmetrics
Provides-Extra: colorama
Requires-Dist: colorama>=0.4.3; extra == "colorama"
Provides-Extra: scikit-learn
Requires-Dist: scikit-learn>=0.23.2; extra == "scikit-learn"
Provides-Extra: tensorboard
Requires-Dist: tensorboard>=2.4.0; extra == "tensorboard"
Provides-Extra: tensorboardx
Requires-Dist: tensorboardX>=2.1; extra == "tensorboardx"
Provides-Extra: torchvision
Requires-Dist: torchvision>=0.8.1; extra == "torchvision"
Provides-Extra: pandas
Requires-Dist: pandas>=2.0.0.0; extra == "pandas"
Provides-Extra: mlflow
Requires-Dist: mlflow>=1.12.1; extra == "mlflow"
Dynamic: author
Dynamic: author-email
Dynamic: classifier
Dynamic: description
Dynamic: description-content-type
Dynamic: download-url
Dynamic: home-page
Dynamic: license
Dynamic: license-file
Dynamic: provides-extra
Dynamic: requires-dist
Dynamic: requires-python
Dynamic: summary
